{
  "$schema": "https://schema.tauri.app/config/2",
  "productName": "Kitstory Lite",
  "version": "0.1.0",
  "identifier": "com.fusky-labs.kitstory-lite",
  "build": {
    "beforeDevCommand": "pnpm dev",
    "devUrl": "http://localhost:1320",
    "beforeBuildCommand": "pnpm build",
    "frontendDist": "../build"
  },
  "app": {
    "windows": [
      {
        "title": "Kitstory Lite",
        "width": 1200,
        "height": 700,
        "decorations": false,
        "devtools": true,
        "zoomHotkeysEnabled": true
      }
    ],
    "security": {
      "csp": null
    }
  },
  "bundle": {
    "active": true,
    "targets": "all",
    "icon": ["icons/32x32.png", "icons/128x128.png", "icons/128x128@2x.png", "icons/icon.icns", "icons/icon.ico"]
  }
}
